goat_plugins/inch1/__init__.py
goat_plugins/inch1/parameters.py
goat_plugins/inch1/service.py
goat_sdk_plugin_1inch-0.1.1.dist-info/METADATA
goat_sdk_plugin_1inch-0.1.1.dist-info/WHEEL
goat_sdk_plugin_1inch-0.1.1.dist-info/RECORD
