Metadata-Version: 2.1
Name: goat-sdk-plugin-1inch
Version: 0.1.1
Summary: 1inch plugin for GOAT SDK
Home-page: https://ohmygoat.dev/
Keywords: goat,sdk,web3,agents,ai,1inch
Author: GOAT SDK Team
Requires-Python: >=3.10,<4.0
Classifier: Programming Language :: Python :: 3
Classifier: Programming Language :: Python :: 3.10
Classifier: Programming Language :: Python :: 3.11
Classifier: Programming Language :: Python :: 3.12
Requires-Dist: aiohttp (>=3.8.6,<4.0.0)
Requires-Dist: goat-sdk (>=0.1.1,<0.2.0)
Project-URL: Bug Tracker, https://github.com/goat-sdk/goat/issues
Project-URL: Repository, https://github.com/goat-sdk/goat
